{
  "nodes": {
    "SitePage /dev-404-page/": {
      "layout": "index",
      "jsonName": "dev-404-page.json",
      "internalComponentName": "ComponentDev404Page",
      "path": "/dev-404-page/",
      "component": "/Users/johnbritti/Documents/web/portfolio/.cache/dev-404-page.js",
      "componentChunkName": "component---cache-dev-404-page-js",
      "context": {},
      "pluginCreator___NODE": "Plugin dev-404-page",
      "pluginCreatorId": "Plugin dev-404-page",
      "componentPath": "/Users/johnbritti/Documents/web/portfolio/.cache/dev-404-page.js",
      "id": "SitePage /dev-404-page/",
      "parent": "SOURCE",
      "children": [],
      "internal": {
        "type": "SitePage",
        "contentDigest": "c30b5ef70db8b58a47caa9e291952017",
        "description": "Plugin dev-404-page",
        "owner": "internal-data-bridge"
      }
    },
    "Plugin dev-404-page": {
      "resolve": "/Users/johnbritti/Documents/web/portfolio/node_modules/gatsby/dist/internal-plugins/dev-404-page",
      "id": "Plugin dev-404-page",
      "name": "dev-404-page",
      "version": "1.0.0",
      "pluginOptions": {
        "plugins": []
      },
      "nodeAPIs": [
        "createPagesStatefully"
      ],
      "browserAPIs": [],
      "ssrAPIs": [],
      "pluginFilepath": "/Users/johnbritti/Documents/web/portfolio/node_modules/gatsby/dist/internal-plugins/dev-404-page",
      "packageJson": {
        "name": "dev-404-page",
        "description": "Internal plugin to add a 404 page in development with helpful information",
        "version": "1.0.0",
        "main": "index.js",
        "author": "Kyle Mathews <mathews.kyle@gmail.com>",
        "license": "MIT",
        "dependencies": [],
        "devDependencies": [],
        "peerDependencies": [],
        "optionalDependecies": [],
        "bundledDependecies": []
      },
      "parent": "SOURCE",
      "children": [],
      "internal": {
        "contentDigest": "4d5667942fd71a033516cb7d0edbd909",
        "type": "SitePlugin",
        "owner": "internal-data-bridge"
      }
    },
    "Plugin component-layout-creator": {
      "resolve": "/Users/johnbritti/Documents/web/portfolio/node_modules/gatsby/dist/internal-plugins/component-layout-creator",
      "id": "Plugin component-layout-creator",
      "name": "component-layout-creator",
      "version": "1.0.0",
      "pluginOptions": {
        "plugins": []
      },
      "nodeAPIs": [
        "createLayouts"
      ],
      "browserAPIs": [],
      "ssrAPIs": [],
      "pluginFilepath": "/Users/johnbritti/Documents/web/portfolio/node_modules/gatsby/dist/internal-plugins/component-layout-creator",
      "packageJson": {
        "name": "component-layout-creator",
        "description": "An internal Gatsby plugin that creates pages from component files in src/layouts",
        "version": "1.0.0",
        "main": "index.js",
        "keywords": [
          "gatsby",
          "gatsby-plugin"
        ],
        "author": "Kyle Mathews <mathews.kyle@gmail.com>",
        "license": "MIT",
        "dependencies": [],
        "devDependencies": [],
        "peerDependencies": [],
        "optionalDependecies": [],
        "bundledDependecies": []
      },
      "parent": "SOURCE",
      "children": [],
      "internal": {
        "contentDigest": "f631556250998426960aba2abd5fead8",
        "type": "SitePlugin",
        "owner": "internal-data-bridge"
      }
    },
    "Plugin internal-data-bridge": {
      "resolve": "/Users/johnbritti/Documents/web/portfolio/node_modules/gatsby/dist/internal-plugins/internal-data-bridge",
      "id": "Plugin internal-data-bridge",
      "name": "internal-data-bridge",
      "version": "1.0.0",
      "pluginOptions": {
        "plugins": []
      },
      "nodeAPIs": [
        "sourceNodes",
        "onCreatePage"
      ],
      "browserAPIs": [],
      "ssrAPIs": [],
      "pluginFilepath": "/Users/johnbritti/Documents/web/portfolio/node_modules/gatsby/dist/internal-plugins/internal-data-bridge",
      "packageJson": {
        "name": "internal-data-bridge",
        "description": "An internal Gatsby plugin which creates data nodes from internal data",
        "version": "1.0.0",
        "main": "index.js",
        "author": "Kyle Mathews <mathews.kyle@gmail.com>",
        "license": "MIT",
        "dependencies": [],
        "devDependencies": [],
        "peerDependencies": [],
        "optionalDependecies": [],
        "bundledDependecies": []
      },
      "parent": "SOURCE",
      "children": [],
      "internal": {
        "contentDigest": "fc4ad0fcebf7e6c751a9e0a1bf9a3200",
        "type": "SitePlugin",
        "owner": "internal-data-bridge"
      }
    },
    "Plugin prod-404": {
      "resolve": "/Users/johnbritti/Documents/web/portfolio/node_modules/gatsby/dist/internal-plugins/prod-404",
      "id": "Plugin prod-404",
      "name": "prod-404",
      "version": "1.0.0",
      "pluginOptions": {
        "plugins": []
      },
      "nodeAPIs": [
        "onCreatePage"
      ],
      "browserAPIs": [],
      "ssrAPIs": [],
      "pluginFilepath": "/Users/johnbritti/Documents/web/portfolio/node_modules/gatsby/dist/internal-plugins/prod-404",
      "packageJson": {
        "name": "prod-404",
        "description": "Internal plugin to detect various flavors of 404 pages and ensure there's a 404.html path created as well to ensure compatability with static hosts",
        "version": "1.0.0",
        "main": "index.js",
        "author": "Kyle Mathews <mathews.kyle@gmail.com>",
        "license": "MIT",
        "dependencies": [],
        "devDependencies": [],
        "peerDependencies": [],
        "optionalDependecies": [],
        "bundledDependecies": []
      },
      "parent": "SOURCE",
      "children": [],
      "internal": {
        "contentDigest": "392cba5983a4beb85298ea94f3b1bcad",
        "type": "SitePlugin",
        "owner": "internal-data-bridge"
      }
    },
    "Plugin query-runner": {
      "resolve": "/Users/johnbritti/Documents/web/portfolio/node_modules/gatsby/dist/internal-plugins/query-runner",
      "id": "Plugin query-runner",
      "name": "query-runner",
      "version": "1.0.0",
      "pluginOptions": {
        "plugins": []
      },
      "nodeAPIs": [
        "onCreatePage",
        "onCreateLayout"
      ],
      "browserAPIs": [],
      "ssrAPIs": [],
      "pluginFilepath": "/Users/johnbritti/Documents/web/portfolio/node_modules/gatsby/dist/internal-plugins/query-runner",
      "packageJson": {
        "name": "query-runner",
        "description": "Internal plugin for running queries",
        "version": "1.0.0",
        "main": "index.js",
        "author": "",
        "license": "MIT",
        "dependencies": [],
        "devDependencies": [],
        "peerDependencies": [],
        "optionalDependecies": [],
        "bundledDependecies": []
      },
      "parent": "SOURCE",
      "children": [],
      "internal": {
        "contentDigest": "f0f64280f5b2597e2fe7a65a8bd7a1fd",
        "type": "SitePlugin",
        "owner": "internal-data-bridge"
      }
    },
    "Plugin gatsby-plugin-react-helmet": {
      "resolve": "/Users/johnbritti/Documents/web/portfolio/node_modules/gatsby-plugin-react-helmet",
      "id": "Plugin gatsby-plugin-react-helmet",
      "name": "gatsby-plugin-react-helmet",
      "version": "2.0.11",
      "pluginOptions": {
        "plugins": []
      },
      "nodeAPIs": [],
      "browserAPIs": [],
      "ssrAPIs": [
        "onRenderBody"
      ],
      "pluginFilepath": "/Users/johnbritti/Documents/web/portfolio/node_modules/gatsby-plugin-react-helmet",
      "packageJson": {
        "name": "gatsby-plugin-react-helmet",
        "description": "Manage document head data with react-helmet. Provides drop-in server rendering support for Gatsby.",
        "version": "2.0.11",
        "main": "index.js",
        "keywords": [
          "gatsby",
          "gatsby-plugin",
          "favicon",
          "react-helmet",
          "seo",
          "document",
          "head",
          "title",
          "meta",
          "link",
          "script",
          "base",
          "noscript",
          "style"
        ],
        "author": "Kyle Mathews <matthews.kyle@gmail.com>",
        "license": "MIT",
        "dependencies": [
          {
            "name": "babel-runtime",
            "version": "^6.26.0"
          }
        ],
        "devDependencies": [
          {
            "name": "babel-cli",
            "version": "^6.26.0"
          },
          {
            "name": "cross-env",
            "version": "^5.0.5"
          }
        ],
        "peerDependencies": [
          {
            "name": "gatsby",
            "version": "^1.0.0"
          },
          {
            "name": "react-helmet",
            "version": ">=5.1.3"
          }
        ],
        "optionalDependecies": [],
        "bundledDependecies": []
      },
      "parent": "SOURCE",
      "children": [],
      "internal": {
        "contentDigest": "3dc38fd30dd455bf77f4e7b3275b3d5c",
        "type": "SitePlugin",
        "owner": "internal-data-bridge"
      }
    },
    "Plugin default-site-plugin": {
      "resolve": "/Users/johnbritti/Documents/web/portfolio",
      "id": "Plugin default-site-plugin",
      "name": "default-site-plugin",
      "version": "a77c4ad8ddfd7c099694aea8fa852ba5",
      "pluginOptions": {
        "plugins": []
      },
      "nodeAPIs": [],
      "browserAPIs": [],
      "ssrAPIs": [],
      "pluginFilepath": "/Users/johnbritti/Documents/web/portfolio",
      "packageJson": {
        "name": "gatsby-starter-default",
        "description": "Gatsby default starter",
        "version": "1.0.0",
        "keywords": [
          "gatsby"
        ],
        "author": "Kyle Mathews <mathews.kyle@gmail.com>",
        "license": "MIT",
        "dependencies": [
          {
            "name": "gatsby",
            "version": "^1.9.277"
          },
          {
            "name": "gatsby-link",
            "version": "^1.6.46"
          },
          {
            "name": "gatsby-plugin-react-helmet",
            "version": "^2.0.11"
          },
          {
            "name": "react-helmet",
            "version": "^5.2.0"
          }
        ],
        "devDependencies": [
          {
            "name": "prettier",
            "version": "^1.13.7"
          }
        ],
        "peerDependencies": [],
        "optionalDependecies": [],
        "bundledDependecies": []
      },
      "parent": "SOURCE",
      "children": [],
      "internal": {
        "contentDigest": "8c0b40ddebf72f9ff926e102df3ae375",
        "type": "SitePlugin",
        "owner": "internal-data-bridge"
      }
    },
    "Plugin gatsby-plugin-page-creator": {
      "resolve": "/Users/johnbritti/Documents/web/portfolio/node_modules/gatsby-plugin-page-creator",
      "id": "Plugin gatsby-plugin-page-creator",
      "name": "gatsby-plugin-page-creator",
      "version": "1.0.1",
      "pluginOptions": {
        "plugins": [],
        "path": "/Users/johnbritti/Documents/web/portfolio/src/pages",
        "pathCheck": false
      },
      "nodeAPIs": [
        "createPagesStatefully"
      ],
      "browserAPIs": [],
      "ssrAPIs": [],
      "pluginFilepath": "/Users/johnbritti/Documents/web/portfolio/node_modules/gatsby-plugin-page-creator",
      "packageJson": {
        "name": "gatsby-plugin-page-creator",
        "description": "Gatsby plugin that automatically creates pages from React components in specified directories",
        "version": "1.0.1",
        "main": "index.js",
        "keywords": [
          "gatsby",
          "gatsby-plugin"
        ],
        "author": "Kyle Mathews <mathews.kyle@gmail.com>",
        "license": "MIT",
        "dependencies": [
          {
            "name": "babel-runtime",
            "version": "^6.26.0"
          },
          {
            "name": "bluebird",
            "version": "^3.5.0"
          },
          {
            "name": "chokidar",
            "version": "^1.7.0"
          },
          {
            "name": "glob",
            "version": "^7.1.1"
          },
          {
            "name": "lodash",
            "version": "^4.17.4"
          },
          {
            "name": "parse-filepath",
            "version": "^1.0.1"
          },
          {
            "name": "slash",
            "version": "^1.0.0"
          }
        ],
        "devDependencies": [
          {
            "name": "babel-cli",
            "version": "^6.26.0"
          },
          {
            "name": "cross-env",
            "version": "^5.0.5"
          }
        ],
        "peerDependencies": [],
        "optionalDependecies": [],
        "bundledDependecies": []
      },
      "parent": "SOURCE",
      "children": [],
      "internal": {
        "contentDigest": "f55aab92f628e75de74d517b4c02f6de",
        "type": "SitePlugin",
        "owner": "internal-data-bridge"
      }
    },
    "Site": {
      "siteMetadata": {
        "title": "Gatsby Default Starter"
      },
      "port": "8000",
      "host": "localhost",
      "pathPrefix": "",
      "polyfill": true,
      "buildTime": "2018-09-07T15:40:29.947Z",
      "id": "Site",
      "parent": "SOURCE",
      "children": [],
      "internal": {
        "contentDigest": "e161ff5f1bed5fdbe43b53c0de3c0d11",
        "type": "Site",
        "owner": "internal-data-bridge"
      }
    },
    "SitePage /404/": {
      "layout": "index",
      "jsonName": "404.json",
      "internalComponentName": "Component404",
      "path": "/404/",
      "component": "/Users/johnbritti/Documents/web/portfolio/src/pages/404.js",
      "componentChunkName": "component---src-pages-404-js",
      "context": {},
      "pluginCreator___NODE": "Plugin gatsby-plugin-page-creator",
      "pluginCreatorId": "Plugin gatsby-plugin-page-creator",
      "componentPath": "/Users/johnbritti/Documents/web/portfolio/src/pages/404.js",
      "id": "SitePage /404/",
      "parent": "SOURCE",
      "children": [],
      "internal": {
        "type": "SitePage",
        "contentDigest": "7a030015b80407d2fa112a7196f28bcb",
        "description": "Plugin gatsby-plugin-page-creator",
        "owner": "internal-data-bridge"
      }
    },
    "SitePage /": {
      "layout": "index",
      "jsonName": "index.json",
      "internalComponentName": "ComponentIndex",
      "path": "/",
      "component": "/Users/johnbritti/Documents/web/portfolio/src/pages/index.js",
      "componentChunkName": "component---src-pages-index-js",
      "context": {},
      "pluginCreator___NODE": "Plugin gatsby-plugin-page-creator",
      "pluginCreatorId": "Plugin gatsby-plugin-page-creator",
      "componentPath": "/Users/johnbritti/Documents/web/portfolio/src/pages/index.js",
      "id": "SitePage /",
      "parent": "SOURCE",
      "children": [],
      "internal": {
        "type": "SitePage",
        "contentDigest": "78016dddae5b7d2a547026c3b85b667a",
        "description": "Plugin gatsby-plugin-page-creator",
        "owner": "internal-data-bridge"
      }
    },
    "SitePage /page-2/": {
      "layout": "index",
      "jsonName": "page-2.json",
      "internalComponentName": "ComponentPage2",
      "path": "/page-2/",
      "component": "/Users/johnbritti/Documents/web/portfolio/src/pages/page-2.js",
      "componentChunkName": "component---src-pages-page-2-js",
      "context": {},
      "pluginCreator___NODE": "Plugin gatsby-plugin-page-creator",
      "pluginCreatorId": "Plugin gatsby-plugin-page-creator",
      "componentPath": "/Users/johnbritti/Documents/web/portfolio/src/pages/page-2.js",
      "id": "SitePage /page-2/",
      "parent": "SOURCE",
      "children": [],
      "internal": {
        "type": "SitePage",
        "contentDigest": "b66c49faa4437cd263bf89a9fe864f8e",
        "description": "Plugin gatsby-plugin-page-creator",
        "owner": "internal-data-bridge"
      }
    },
    "SitePage /404.html": {
      "layout": "index",
      "jsonName": "404-html.json",
      "internalComponentName": "Component404Html",
      "path": "/404.html",
      "component": "/Users/johnbritti/Documents/web/portfolio/src/pages/404.js",
      "componentChunkName": "component---src-pages-404-js",
      "context": {},
      "pluginCreator___NODE": "Plugin prod-404",
      "pluginCreatorId": "Plugin prod-404",
      "componentPath": "/Users/johnbritti/Documents/web/portfolio/src/pages/404.js",
      "id": "SitePage /404.html",
      "parent": "SOURCE",
      "children": [],
      "internal": {
        "type": "SitePage",
        "contentDigest": "d59774c49303b678364c104f425e0470",
        "description": "Plugin prod-404",
        "owner": "internal-data-bridge"
      }
    }
  },
  "status": {
    "plugins": {},
    "PLUGINS_HASH": "673643eb1ce4b27a13383d8dd93b20b9"
  },
  "componentDataDependencies": {
    "nodes": {
      "Site": [
        "LAYOUT___index"
      ]
    },
    "connections": {
      "SitePage": [
        "/dev-404-page/"
      ]
    }
  }
}